doji/__init__.py
doji/py.typed
doji-0.0.2.dist-info/METADATA
doji-0.0.2.dist-info/WHEEL
doji-0.0.2.dist-info/RECORD
