Metadata-Version: 2.4
Name: doji
Version: 0.0.2
Summary: Work in progress
Author-email: richardxhong <hongxrichard@gmail.com>
Requires-Python: >=3.13
Requires-Dist: polars>=1.24.0
